hardware/basic/pim_opcodes.svh
//=====================================================================
// File: pim_opcodes.svh
// Purpose: Shared command packet definitions and opcode constants for
//          the PIM sequencer / controller RTL.
// Usage : `include "pim_opcodes.svh" in any SV file that needs these.
//=====================================================================

`ifndef PIM_OPCODES_SVH
`define PIM_OPCODES_SVH

// -------------------------------
// Command packet layout (64 bits)
// -------------------------------
// Bit ranges (big picture):
// [63:56]  opcode     (8 bits)   -- operation selector
// [55:48]  flags      (8 bits)   -- per-command flags (reserved / mode bits)
// [47:16]  addr       (32 bits)  -- address or immediate (zero-extend to 64-bit if needed)
// [15:0]   mac_count  (16 bits)  -- number of MAC operations for compute commands
//
// Note: The exact wire packing / endianness must match how you construct
//       cmd_data in testbench / CPU logic. The RTL code assumes the
//       LSB 16 bits are mac_count, etc.
// -------------------------------

typedef struct packed {
    logic [7:0]  opcode;
    logic [7:0]  flags;
    logic [31:0] addr;
    logic [15:0] mac_count;
} pim_cmd_t;

// -------------------------------
// Opcode definitions (8-bit)
// -------------------------------
// Choose values that are easy to spot in simulation prints (hex-coded).
localparam logic [7:0] OPC_FETCH_INPUT    = 8'h01;
localparam logic [7:0] OPC_FETCH_WEIGHTS  = 8'h02;
localparam logic [7:0] OPC_COMPUTE        = 8'h03;
localparam logic [7:0] OPC_STORE_OUTPUT   = 8'h04;
localparam logic [7:0] OPC_EXECUTE_SEQ    = 8'h05; // optional meta-op from CPU to sequencer

// -------------------------------
// Helpful macros / extraction helpers
// -------------------------------
// You can cast a 64-bit vector into pim_cmd_t like:
//   pim_cmd_t cmd = pim_cmd_t'(cmd64);
// And access fields as cmd.opcode, cmd.addr, cmd.mac_count, etc.
//
// Alternatively, if using bit-slices:
//   opcode    = cmd64[63:56];
//   flags     = cmd64[55:48];
//   addr      = cmd64[47:16];
//   mac_count = cmd64[15:0];
//
// The RTL modules provided use pim_cmd_t'(cmd_data) where convenient.
//
// -------------------------------
`endif // PIM_OPCODES_SVH

hardware/basic/sequencer_accelerator.sv
//=====================================================================
// File: sequencer_accelerator.sv
// Purpose: A simplified, single-module PIM accelerator that demonstrates
//          the performance difference between micromanagement and a
//          hardware command sequencer.
// Notes: Icarus-friendly edits: use shift+mask instead of variable part-select,
//        and use plain always for assertion block to avoid a noisy iverilog warning.
//=====================================================================

`timescale 1ns / 1ps
`include "pim_opcodes.svh"

module sequencer_accelerator #(
    parameter int MICROPROG_LEN       = 4,
    parameter int FIFO_DEPTH          = 4,
    parameter int IO_CYCLES           = 150,
    parameter int COMPUTE_CYCLES      = 400
)(
    input  logic clk,
    input  logic rst_n,

    // --- CPU Interface ---
    input  logic cpu_mode, // 0 for Micromanagement, 1 for Sequencer
    input  logic cpu_cmd_valid,
    input  logic [64*MICROPROG_LEN-1:0] cpu_cmd_data,
    output logic cpu_cmd_ready,     

    // --- Status ---
    output logic accelerator_busy,
    output logic layer_done
);

    // --- Parameter Validation ---
    initial begin
        if (MICROPROG_LEN < 1) $fatal(1, "MICROPROG_LEN must be >= 1");
        if (FIFO_DEPTH < 1) $fatal(1, "FIFO_DEPTH must be >= 1");
    end

    // Modes
    localparam MICROMANAGEMENT_MODE = 1'b0;
    localparam SEQUENCER_MODE       = 1'b1;

    localparam int OP_IDX_W = (MICROPROG_LEN > 1) ? $clog2(MICROPROG_LEN) : 1;
    localparam int CMD_WIDTH = 64;

    // ---- Safe pointer/count widths to support FIFO_DEPTH == 1
    localparam int PTR_W   = (FIFO_DEPTH > 1) ? $clog2(FIFO_DEPTH) : 1;
    localparam int COUNT_W = (FIFO_DEPTH+1 > 1) ? $clog2(FIFO_DEPTH+1) : 1;

    //=============================================================
    // 1. Internal FIFO for Sequencer Mode
    //=============================================================
    logic [CMD_WIDTH*MICROPROG_LEN-1:0] fifo_mem [0:FIFO_DEPTH-1];
    logic [PTR_W-1:0] wr_ptr, rd_ptr;
    logic [COUNT_W-1:0] fifo_count;
    logic fifo_full, fifo_empty;
    logic fifo_write_en, fifo_read_en;

    assign fifo_full = (fifo_count == FIFO_DEPTH);
    assign fifo_empty = (fifo_count == 0);

    // combinational read address to avoid read-after-write confusion
    logic [PTR_W-1:0] fifo_rd_addr;
    assign fifo_rd_addr = rd_ptr;

    always_ff @(posedge clk or negedge rst_n) begin
        if (!rst_n) begin
            wr_ptr <= '0;
            rd_ptr <= '0;
            fifo_count <= '0;
        end else begin
            if (fifo_write_en) begin
                fifo_mem[wr_ptr] <= cpu_cmd_data;
                wr_ptr <= wr_ptr + 1;
            end
            if (fifo_read_en) begin
                rd_ptr <= rd_ptr + 1;
            end

            // Corrected fifo_count update logic
            if (fifo_write_en && !fifo_read_en)      fifo_count <= fifo_count + 1;
            else if (!fifo_write_en && fifo_read_en) fifo_count <= fifo_count - 1;
            // if both happen, fifo_count unchanged
        end
    end

    // Assertions for FIFO overflow/underflow (gated by reset)
    // Use plain always to avoid iverilog "cannot be synthesized in always_ff" warning.
    `ifndef VERILATOR
    always @(posedge clk or negedge rst_n) begin
        if (!rst_n) ;
        else begin
            if (fifo_write_en && fifo_full) $fatal(2, "FIFO Overflow detected!");
            if (fifo_read_en  && fifo_empty) $fatal(2, "FIFO Underflow detected!");
        end
    end
    `endif

    //=============================================================
    // 2. Simple PIM Execution Unit (Behavioral Model)
    //=============================================================
    // Use simple logic signals for state to stay iverilog-friendly
    localparam EXEC_IDLE = 1'b0;
    localparam EXEC_BUSY = 1'b1;
    logic exec_state_q, exec_state_d;
    logic [15:0] exec_timer_q, exec_timer_d;
    logic exec_start; // handshake for starting an exec
    logic [CMD_WIDTH-1:0] exec_cmd_in;
    logic exec_done;

    always_ff @(posedge clk or negedge rst_n) begin
        if (!rst_n) begin
            exec_state_q <= EXEC_IDLE;
            exec_timer_q <= '0;
        end else begin
            exec_state_q <= exec_state_d;
            exec_timer_q <= exec_timer_d;
        end
    end

    // Use opcode slice instead of type-cast to pim_cmd_t (more portable)
    always_comb begin
        exec_state_d = exec_state_q;
        exec_timer_d = exec_timer_q;
        exec_done = 1'b0;

        case (exec_state_q)
            EXEC_IDLE: begin
                if (exec_start) begin
                    exec_state_d = EXEC_BUSY;
                    case (exec_cmd_in[CMD_WIDTH-1 -: 8]) // opcode located at bits [63:56]
                        OPC_FETCH_INPUT, OPC_FETCH_WEIGHTS, OPC_STORE_OUTPUT: exec_timer_d = IO_CYCLES;
                        OPC_COMPUTE: exec_timer_d = COMPUTE_CYCLES;
                        default: exec_timer_d = 1;
                    endcase
                end
            end
            EXEC_BUSY: begin
                if (exec_timer_q <= 1) begin
                    exec_state_d = EXEC_IDLE;
                    exec_done = 1'b1;
                end else begin
                    exec_timer_d = exec_timer_q - 1;
                end
            end
            default: begin
                exec_state_d = EXEC_IDLE;
                exec_timer_d = '0;
            end
        endcase
    end

    //=============================================================
    // 2b. Exec command extraction (avoid variable part-select warning)
    //=============================================================
    // We extract the CMD_WIDTH-bit command by shifting down by (op_idx_q * CMD_WIDTH)
    // and masking the lowest CMD_WIDTH bits. This is portable and avoids the
    // "constant selects in always_*" complaint from some iverilog versions.
    logic [CMD_WIDTH-1:0] exec_cmd_mask;
    assign exec_cmd_mask = {CMD_WIDTH{1'b1}};

    always_comb begin
        // shift right by op_idx_q * CMD_WIDTH, then mask low bits
        exec_cmd_in = (microprog_reg_q >> (op_idx_q * CMD_WIDTH)) & exec_cmd_mask;
    end

    //=============================================================
    // 3. Main Sequencer FSM (The "Brain")
    //=============================================================
    // small encoded FSM (2-bit)
    localparam [1:0] S_IDLE  = 2'b00;
    localparam [1:0] S_FETCH = 2'b01;
    localparam [1:0] S_ISSUE = 2'b10;
    localparam [1:0] S_WAIT  = 2'b11;
    logic [1:0] state_q, state_d;

    logic [CMD_WIDTH*MICROPROG_LEN-1:0] microprog_reg_q;
    logic [OP_IDX_W-1:0] op_idx_q, op_idx_d;
    logic layer_done_r;

    // --- Control Signal Assignments ---
    assign cpu_cmd_ready = (state_q == S_IDLE) &&
                           ((cpu_mode == MICROMANAGEMENT_MODE) ||
                            (cpu_mode == SEQUENCER_MODE && !fifo_full));

    // accelerator_busy: indicates either active execution or queued work pending
    assign accelerator_busy = (state_q != S_IDLE) || (exec_state_q != EXEC_IDLE) || (cpu_mode == SEQUENCER_MODE && !fifo_empty);

    assign layer_done = layer_done_r;

    // exec_start: FSM in ISSUE and exec is idle.
    assign exec_start = (state_q == S_ISSUE) && (exec_state_q == EXEC_IDLE);

    // FIFO enables: include cpu_cmd_ready to honor the handshake
    assign fifo_write_en = (cpu_mode == SEQUENCER_MODE) && cpu_cmd_valid && cpu_cmd_ready;
    assign fifo_read_en  = (state_q == S_FETCH) && (cpu_mode == SEQUENCER_MODE) && !fifo_empty;

    always_ff @(posedge clk or negedge rst_n) begin
        if (!rst_n) begin
            state_q <= S_IDLE;
            op_idx_q <= '0;
            layer_done_r <= 1'b0;
            microprog_reg_q <= '0;
        end else begin
            state_q <= state_d;
            op_idx_q <= op_idx_d;

            // one-cycle pulse for layer_done (registered)
            layer_done_r <= (state_q == S_WAIT) && exec_done &&
                            ((cpu_mode == MICROMANAGEMENT_MODE) || (op_idx_q == MICROPROG_LEN - 1));

            if (state_d == S_FETCH) begin
                if (cpu_mode == MICROMANAGEMENT_MODE) begin
                    microprog_reg_q <= {{(CMD_WIDTH*(MICROPROG_LEN-1)){1'b0}}, cpu_cmd_data[CMD_WIDTH-1:0]};
                end else begin
                    // read from FIFO at the current rd_ptr (combinational fifo_rd_addr)
                    microprog_reg_q <= fifo_mem[fifo_rd_addr];
                end
            end
        end
    end

    always_comb begin
        state_d = state_q;
        op_idx_d = op_idx_q;

        case (state_q)
            S_IDLE: begin
                if ((cpu_mode == SEQUENCER_MODE && !fifo_empty) ||
                    (cpu_mode == MICROMANAGEMENT_MODE && cpu_cmd_valid && cpu_cmd_ready)) begin
                    state_d = S_FETCH;
                    op_idx_d = '0;
                end
            end
            S_FETCH: begin
                state_d = S_ISSUE;
            end
            S_ISSUE: begin
                // If exec accepts the start condition, move to wait
                if (exec_start) begin
                    state_d = S_WAIT;
                end
            end
            S_WAIT: begin
                if (exec_done) begin
                    if ((cpu_mode == MICROMANAGEMENT_MODE) || (op_idx_q == MICROPROG_LEN - 1)) begin
                        state_d = S_IDLE;
                    end else begin
                        state_d = S_ISSUE; // Go to next micro-op
                        op_idx_d = op_idx_q + 1;
                    end
                end
            end
            default: begin
                state_d = S_IDLE;
                op_idx_d = '0;
            end
        endcase
    end

endmodule

hardware/basic/tb_sequencer_accelerator.sv
//=====================================================================
// File: tb_sequencer_accelerator.sv
// Purpose: Testbench for the simplified PIM accelerator.
// Icarus/iverilog-friendly version.
//=====================================================================

`timescale 1ns / 1ps
`include "pim_opcodes.svh"

module tb_sequencer_accelerator;

    localparam MICROPROG_LEN = 4;
    
    reg clk = 0;
    reg rst_n;
    
    // Inputs to DUT are regs, outputs are wires
    reg cpu_mode;
    reg cpu_cmd_valid;
    reg [64*MICROPROG_LEN-1:0] cpu_cmd_data;
    wire cpu_cmd_ready;
    wire accelerator_busy;
    wire layer_done;

    // microprog declared at module scope (iverilog compatibility)
    reg [64*MICROPROG_LEN-1:0] microprog;

    // Instantiate DUT (port names match)
    sequencer_accelerator #(.MICROPROG_LEN(MICROPROG_LEN)) dut (
        .clk(clk),
        .rst_n(rst_n),
        .cpu_mode(cpu_mode),
        .cpu_cmd_valid(cpu_cmd_valid),
        .cpu_cmd_data(cpu_cmd_data),
        .cpu_cmd_ready(cpu_cmd_ready),
        .accelerator_busy(accelerator_busy),
        .layer_done(layer_done)
    );

    always #5 clk = ~clk; // 10ns period (100 MHz)

    // Reset task: blocking assignments are fine in TB
    task reset_dut;
        begin
            rst_n = 1'b0;
            cpu_mode = 0;
            cpu_cmd_valid = 0;
            cpu_cmd_data = 0;
            #20;
            rst_n = 1'b1;
            #10;
            $display("[%0t] Testbench: Reset complete.", $time);
        end
    endtask

    // make_cmd helper - Verilog-2001 function style
    function [63:0] make_cmd;
        input [7:0] opcode;
        begin
            make_cmd = {opcode, 56'h0};
        end
    endfunction

    // Helper: build microprogram (op0 is first-executed -> LSB)
    function [64*MICROPROG_LEN-1:0] build_microprog;
        input [63:0] op3; // Last op (MSB)
        input [63:0] op2;
        input [63:0] op1;
        input [63:0] op0; // First op (LSB)
        begin
            build_microprog = {op3, op2, op1, op0};
        end
    endfunction

    initial begin
        integer micro_start_time, micro_end_time;
        integer seq_start_time, seq_end_time;
        integer num_layers;
        integer i;
        real speedup;

        num_layers = 3;

        $dumpfile("accelerator_tb.vcd");
        $dumpvars(0, tb_sequencer_accelerator);
        
        reset_dut();

        // --- Test 1: Micromanagement Mode ---
        $display("\n--- Starting Micromanagement Test (%0d layers) ---", num_layers);
        cpu_mode = 0;
        micro_start_time = $time;
        
        for (i = 0; i < num_layers; i = i + 1) begin
            $display("[%0t] Micromanagement: Starting Layer %0d", $time, i+1);
            
            @(posedge clk);
            cpu_cmd_valid = 1;
            cpu_cmd_data = make_cmd(OPC_FETCH_INPUT);
            wait (cpu_cmd_ready);
            @(posedge clk);
            cpu_cmd_valid = 0;
            wait (layer_done);
            $display("[%0t] ...FETCH_INPUT Done.", $time);
            
            @(posedge clk);
            cpu_cmd_valid = 1;
            cpu_cmd_data = make_cmd(OPC_FETCH_WEIGHTS);
            wait (cpu_cmd_ready);
            @(posedge clk);
            cpu_cmd_valid = 0;
            wait (layer_done);
            $display("[%0t] ...FETCH_WEIGHTS Done.", $time);

            @(posedge clk);
            cpu_cmd_valid = 1;
            cpu_cmd_data = make_cmd(OPC_COMPUTE);
            wait (cpu_cmd_ready);
            @(posedge clk);
            cpu_cmd_valid = 0;
            wait (layer_done);
            $display("[%0t] ...COMPUTE Done.", $time);

            @(posedge clk);
            cpu_cmd_valid = 1;
            cpu_cmd_data = make_cmd(OPC_STORE_OUTPUT);
            wait (cpu_cmd_ready);
            @(posedge clk);
            cpu_cmd_valid = 0;
            wait (layer_done);
            $display("[%0t] ...STORE_OUTPUT Done. Layer %0d complete.", $time, i+1);
        end
        micro_end_time = $time;

        // --- Test 2: Sequencer Mode ---
        wait(!accelerator_busy);
        $display("\n--- Starting Sequencer Test (%0d layers) ---", num_layers);
        cpu_mode = 1;
        seq_start_time = $time;
        
        // first op (FETCH_INPUT) must be LSB -> pass as op0 to build_microprog
        microprog = build_microprog(make_cmd(OPC_STORE_OUTPUT), 
                                    make_cmd(OPC_COMPUTE), 
                                    make_cmd(OPC_FETCH_WEIGHTS), 
                                    make_cmd(OPC_FETCH_INPUT));
        
        // Submit all layers to the FIFO as fast as possible (handshake respected)
        for (i = 0; i < num_layers; i = i + 1) begin
            @(posedge clk);
            cpu_cmd_valid = 1;
            cpu_cmd_data = microprog;
            wait (cpu_cmd_ready);
            @(posedge clk);
            cpu_cmd_valid = 0;
            $display("[%0t] Sequencer: Submitted microprogram for Layer %0d.", $time, i+1);
        end

        wait(!accelerator_busy);
        seq_end_time = $time;
        
        // --- Report Results ---
        $display("\n--- Simulation Results ---");
        $display("Micromanagement Total Time: %0d cycles", (micro_end_time - micro_start_time)/10);
        $display("Sequencer Total Time:       %0d cycles", (seq_end_time - seq_start_time)/10);
        
        speedup = $itor(micro_end_time - micro_start_time) / $itor(seq_end_time - seq_start_time);
        $display("Speedup: %.2fx", speedup);
        
        #50;
        $finish;
    end
endmodule

hardware/basic/accelerator_tb.vcd
$date
	Thu Oct 23 23:47:32 2025
$end
$version
	Icarus Verilog
$end
$timescale
	1ps
$end
$scope module tb_sequencer_accelerator $end
$var wire 1 ! layer_done $end
$var wire 1 " cpu_cmd_ready $end
$var wire 1 # accelerator_busy $end
$var parameter 32 $ MICROPROG_LEN $end
$var reg 1 % clk $end
$var reg 256 & cpu_cmd_data [255:0] $end
$var reg 1 ' cpu_cmd_valid $end
$var reg 1 ( cpu_mode $end
$var reg 256 ) microprog [255:0] $end
$var reg 1 * rst_n $end
$scope function build_microprog $end
$var reg 64 + op0 [63:0] $end
$var reg 64 , op1 [63:0] $end
$var reg 64 - op2 [63:0] $end
$var reg 64 . op3 [63:0] $end
$upscope $end
$scope function make_cmd $end
$var reg 8 / opcode [7:0] $end
$upscope $end
$scope module dut $end
$var wire 1 # accelerator_busy $end
$var wire 1 % clk $end
$var wire 256 0 cpu_cmd_data [255:0] $end
$var wire 1 " cpu_cmd_ready $end
$var wire 1 ' cpu_cmd_valid $end
$var wire 1 ( cpu_mode $end
$var wire 64 1 exec_cmd_mask [63:0] $end
$var wire 1 2 exec_start $end
$var wire 2 3 fifo_rd_addr [1:0] $end
$var wire 1 4 fifo_read_en $end
$var wire 1 5 fifo_write_en $end
$var wire 1 ! layer_done $end
$var wire 1 * rst_n $end
$var wire 1 6 fifo_full $end
$var wire 1 7 fifo_empty $end
$var parameter 32 8 CMD_WIDTH $end
$var parameter 32 9 COMPUTE_CYCLES $end
$var parameter 32 : COUNT_W $end
$var parameter 1 ; EXEC_BUSY $end
$var parameter 1 < EXEC_IDLE $end
$var parameter 32 = FIFO_DEPTH $end
$var parameter 32 > IO_CYCLES $end
$var parameter 1 ? MICROMANAGEMENT_MODE $end
$var parameter 32 @ MICROPROG_LEN $end
$var parameter 32 A OP_IDX_W $end
$var parameter 32 B PTR_W $end
$var parameter 1 C SEQUENCER_MODE $end
$var parameter 2 D S_FETCH $end
$var parameter 2 E S_IDLE $end
$var parameter 2 F S_ISSUE $end
$var parameter 2 G S_WAIT $end
$var reg 64 H exec_cmd_in [63:0] $end
$var reg 1 I exec_done $end
$var reg 1 J exec_state_d $end
$var reg 1 K exec_state_q $end
$var reg 16 L exec_timer_d [15:0] $end
$var reg 16 M exec_timer_q [15:0] $end
$var reg 3 N fifo_count [2:0] $end
$var reg 1 O layer_done_r $end
$var reg 256 P microprog_reg_q [255:0] $end
$var reg 2 Q op_idx_d [1:0] $end
$var reg 2 R op_idx_q [1:0] $end
$var reg 2 S rd_ptr [1:0] $end
$var reg 2 T state_d [1:0] $end
$var reg 2 U state_q [1:0] $end
$var reg 2 V wr_ptr [1:0] $end
$upscope $end
$scope begin $unm_blk_4 $end
$var integer 32 W i [31:0] $end
$var integer 32 X micro_end_time [31:0] $end
$var integer 32 Y micro_start_time [31:0] $end
$var integer 32 Z num_layers [31:0] $end
$var integer 32 [ seq_end_time [31:0] $end
$var integer 32 \ seq_start_time [31:0] $end
$var real 1 ] speedup $end
$upscope $end
$scope task reset_dut $end
$upscope $end
$upscope $end
$enddefinitions $end
$comment Show the parameter values. $end
$dumpall
b11 G
b10 F
b0 E
b1 D
1C
b10 B
b10 A
b100 @
0?
b10010110 >
b100 =
0<
1;
b11 :
b110010000 9
b1000000 8
b100 $
$end
#0
$dumpvars
r0 ]
bx \
bx [
b11 Z
bx Y
bx X
bx W
b0 V
b0 U
b0 T
b0 S
b0 R
b0 Q
b0 P
0O
b0 N
b0 M
b0 L
0K
0J
0I
b0 H
17
06
05
04
b0 3
02
b1111111111111111111111111111111111111111111111111111111111111111 1
b0 0
bx /
bx .
bx -
bx ,
bx +
0*
bx )
0(
0'
b0 &
0%
0#
1"
0!
$end
#5000
1%
#10000
0%
#15000
1%
#20000
0%
1*
#25000
1%
#30000
0%
b0 W
b11110 Y
#35000
b1 T
b100000000000000000000000000000000000000000000000000000000 &
b100000000000000000000000000000000000000000000000000000000 0
b1 /
1'
1%
#40000
0%
#45000
1#
b100000000000000000000000000000000000000000000000000000000 H
0"
b100000000000000000000000000000000000000000000000000000000 P
b1 U
b10 T
0'
1%
#50000
0%
#55000
b10010110 L
1J
b11 T
12
b10 U
1%
#60000
0%
#65000
02
b10010101 L
b11 U
b10010110 M
1K
1%
#70000
0%
#75000
b10010100 L
b10010101 M
1%
#80000
0%
#85000
b10010011 L
b10010100 M
1%
#90000
0%
#95000
b10010010 L
b10010011 M
1%
#100000
0%
#105000
b10010001 L
b10010010 M
1%
#110000
0%
#115000
b10010000 L
b10010001 M
1%
#120000
0%
#125000
b10001111 L
b10010000 M
1%
#130000
0%
#135000
b10001110 L
b10001111 M
1%
#140000
0%
#145000
b10001101 L
b10001110 M
1%
#150000
0%
#155000
b10001100 L
b10001101 M
1%
#160000
0%
#165000
b10001011 L
b10001100 M
1%
#170000
0%
#175000
b10001010 L
b10001011 M
1%
#180000
0%
#185000
b10001001 L
b10001010 M
1%
#190000
0%
#195000
b10001000 L
b10001001 M
1%
#200000
0%
#205000
b10000111 L
b10001000 M
1%
#210000
0%
#215000
b10000110 L
b10000111 M
1%
#220000
0%
#225000
b10000101 L
b10000110 M
1%
#230000
0%
#235000
b10000100 L
b10000101 M
1%
#240000
0%
#245000
b10000011 L
b10000100 M
1%
#250000
0%
#255000
b10000010 L
b10000011 M
1%
#260000
0%
#265000
b10000001 L
b10000010 M
1%
#270000
0%
#275000
b10000000 L
b10000001 M
1%
#280000
0%
#285000
b1111111 L
b10000000 M
1%
#290000
0%
#295000
b1111110 L
b1111111 M
1%
#300000
0%
#305000
b1111101 L
b1111110 M
1%
#310000
0%
#315000
b1111100 L
b1111101 M
1%
#320000
0%
#325000
b1111011 L
b1111100 M
1%
#330000
0%
#335000
b1111010 L
b1111011 M
1%
#340000
0%
#345000
b1111001 L
b1111010 M
1%
#350000
0%
#355000
b1111000 L
b1111001 M
1%
#360000
0%
#365000
b1110111 L
b1111000 M
1%
#370000
0%
#375000
b1110110 L
b1110111 M
1%
#380000
0%
#385000
b1110101 L
b1110110 M
1%
#390000
0%
#395000
b1110100 L
b1110101 M
1%
#400000
0%
#405000
b1110011 L
b1110100 M
1%
#410000
0%
#415000
b1110010 L
b1110011 M
1%
#420000
0%
#425000
b1110001 L
b1110010 M
1%
#430000
0%
#435000
b1110000 L
b1110001 M
1%
#440000
0%
#445000
b1101111 L
b1110000 M
1%
#450000
0%
#455000
b1101110 L
b1101111 M
1%
#460000
0%
#465000
b1101101 L
b1101110 M
1%
#470000
0%
#475000
b1101100 L
b1101101 M
1%
#480000
0%
#485000
b1101011 L
b1101100 M
1%
#490000
0%
#495000
b1101010 L
b1101011 M
1%
#500000
0%
#505000
b1101001 L
b1101010 M
1%
#510000
0%
#515000
b1101000 L
b1101001 M
1%
#520000
0%
#525000
b1100111 L
b1101000 M
1%
#530000
0%
#535000
b1100110 L
b1100111 M
1%
#540000
0%
#545000
b1100101 L
b1100110 M
1%
#550000
0%
#555000
b1100100 L
b1100101 M
1%
#560000
0%
#565000
b1100011 L
b1100100 M
1%
#570000
0%
#575000
b1100010 L
b1100011 M
1%
#580000
0%
#585000
b1100001 L
b1100010 M
1%
#590000
0%
#595000
b1100000 L
b1100001 M
1%
#600000
0%
#605000
b1011111 L
b1100000 M
1%
#610000
0%
#615000
b1011110 L
b1011111 M
1%
#620000
0%
#625000
b1011101 L
b1011110 M
1%
#630000
0%
#635000
b1011100 L
b1011101 M
1%
#640000
0%
#645000
b1011011 L
b1011100 M
1%
#650000
0%
#655000
b1011010 L
b1011011 M
1%
#660000
0%
#665000
b1011001 L
b1011010 M
1%
#670000
0%
#675000
b1011000 L
b1011001 M
1%
#680000
0%
#685000
b1010111 L
b1011000 M
1%
#690000
0%
#695000
b1010110 L
b1010111 M
1%
#700000
0%
#705000
b1010101 L
b1010110 M
1%
#710000
0%
#715000
b1010100 L
b1010101 M
1%
#720000
0%
#725000
b1010011 L
b1010100 M
1%
#730000
0%
#735000
b1010010 L
b1010011 M
1%
#740000
0%
#745000
b1010001 L
b1010010 M
1%
#750000
0%
#755000
b1010000 L
b1010001 M
1%
#760000
0%
#765000
b1001111 L
b1010000 M
1%
#770000
0%
#775000
b1001110 L
b1001111 M
1%
#780000
0%
#785000
b1001101 L
b1001110 M
1%
#790000
0%
#795000
b1001100 L
b1001101 M
1%
#800000
0%
#805000
b1001011 L
b1001100 M
1%
#810000
0%
#815000
b1001010 L
b1001011 M
1%
#820000
0%
#825000
b1001001 L
b1001010 M
1%
#830000
0%
#835000
b1001000 L
b1001001 M
1%
#840000
0%
#845000
b1000111 L
b1001000 M
1%
#850000
0%
#855000
b1000110 L
b1000111 M
1%
#860000
0%
#865000
b1000101 L
b1000110 M
1%
#870000
0%
#875000
b1000100 L
b1000101 M
1%
#880000
0%
#885000
b1000011 L
b1000100 M
1%
#890000
0%
#895000
b1000010 L
b1000011 M
1%
#900000
0%
#905000
b1000001 L
b1000010 M
1%
#910000
0%
#915000
b1000000 L
b1000001 M
1%
#920000
0%
#925000
b111111 L
b1000000 M
1%
#930000
0%
#935000
b111110 L
b111111 M
1%
#940000
0%
#945000
b111101 L
b111110 M
1%
#950000
0%
#955000
b111100 L
b111101 M
1%
#960000
0%
#965000
b111011 L
b111100 M
1%
#970000
0%
#975000
b111010 L
b111011 M
1%
#980000
0%
#985000
b111001 L
b111010 M
1%
#990000
0%
#995000
b111000 L
b111001 M
1%
#1000000
0%
#1005000
b110111 L
b111000 M
1%
#1010000
0%
#1015000
b110110 L
b110111 M
1%
#1020000
0%
#1025000
b110101 L
b110110 M
1%
#1030000
0%
#1035000
b110100 L
b110101 M
1%
#1040000
0%
#1045000
b110011 L
b110100 M
1%
#1050000
0%
#1055000
b110010 L
b110011 M
1%
#1060000
0%
#1065000
b110001 L
b110010 M
1%
#1070000
0%
#1075000
b110000 L
b110001 M
1%
#1080000
0%
#1085000
b101111 L
b110000 M
1%
#1090000
0%
#1095000
b101110 L
b101111 M
1%
#1100000
0%
#1105000
b101101 L
b101110 M
1%
#1110000
0%
#1115000
b101100 L
b101101 M
1%
#1120000
0%
#1125000
b101011 L
b101100 M
1%
#1130000
0%
#1135000
b101010 L
b101011 M
1%
#1140000
0%
#1145000
b101001 L
b101010 M
1%
#1150000
0%
#1155000
b101000 L
b101001 M
1%
#1160000
0%
#1165000
b100111 L
b101000 M
1%
#1170000
0%
#1175000
b100110 L
b100111 M
1%
#1180000
0%
#1185000
b100101 L
b100110 M
1%
#1190000
0%
#1195000
b100100 L
b100101 M
1%
#1200000
0%
#1205000
b100011 L
b100100 M
1%
#1210000
0%
#1215000
b100010 L
b100011 M
1%
#1220000
0%
#1225000
b100001 L
b100010 M
1%
#1230000
0%
#1235000
b100000 L
b100001 M
1%
#1240000
0%
#1245000
b11111 L
b100000 M
1%
#1250000
0%
#1255000
b11110 L
b11111 M
1%
#1260000
0%
#1265000
b11101 L
b11110 M
1%
#1270000
0%
#1275000
b11100 L
b11101 M
1%
#1280000
0%
#1285000
b11011 L
b11100 M
1%
#1290000
0%
#1295000
b11010 L
b11011 M
1%
#1300000
0%
#1305000
b11001 L
b11010 M
1%
#1310000
0%
#1315000
b11000 L
b11001 M
1%
#1320000
0%
#1325000
b10111 L
b11000 M
1%
#1330000
0%
#1335000
b10110 L
b10111 M
1%
#1340000
0%
#1345000
b10101 L
b10110 M
1%
#1350000
0%
#1355000
b10100 L
b10101 M
1%
#1360000
0%
#1365000
b10011 L
b10100 M
1%
#1370000
0%
#1375000
b10010 L
b10011 M
1%
#1380000
0%
#1385000
b10001 L
b10010 M
1%
#1390000
0%
#1395000
b10000 L
b10001 M
1%
#1400000
0%
#1405000
b1111 L
b10000 M
1%
#1410000
0%
#1415000
b1110 L
b1111 M
1%
#1420000
0%
#1425000
b1101 L
b1110 M
1%
#1430000
0%
#1435000
b1100 L
b1101 M
1%
#1440000
0%
#1445000
b1011 L
b1100 M
1%
#1450000
0%
#1455000
b1010 L
b1011 M
1%
#1460000
0%
#1465000
b1001 L
b1010 M
1%
#1470000
0%
#1475000
b1000 L
b1001 M
1%
#1480000
0%
#1485000
b111 L
b1000 M
1%
#1490000
0%
#1495000
b110 L
b111 M
1%
#1500000
0%
#1505000
b101 L
b110 M
1%
#1510000
0%
#1515000
b100 L
b101 M
1%
#1520000
0%
#1525000
b11 L
b100 M
1%
#1530000
0%
#1535000
b10 L
b11 M
1%
#1540000
0%
#1545000
b1 L
b10 M
1%
#1550000
0%
#1555000
b0 T
1I
0J
b1 M
1%
#1560000
0%
#1565000
0#
1"
0I
1!
1O
b0 U
0K
1%
#1570000
0%
#1575000
0!
0O
b1 T
b1000000000000000000000000000000000000000000000000000000000 &
b1000000000000000000000000000000000000000000000000000000000 0
b10 /
1'
1%
#1580000
0%
#1585000
1#
b1000000000000000000000000000000000000000000000000000000000 H
0"
b1000000000000000000000000000000000000000000000000000000000 P
b1 U
b10 T
0'
1%
#1590000
0%
#1595000
b10010110 L
1J
b11 T
12
b10 U
1%
#1600000
0%
#1605000
02
b10010101 L
b11 U
b10010110 M
1K
1%
#1610000
0%
#1615000
b10010100 L
b10010101 M
1%
#1620000
0%
#1625000
b10010011 L
b10010100 M
1%
#1630000
0%
#1635000
b10010010 L
b10010011 M
1%
#1640000
0%
#1645000
b10010001 L
b10010010 M
1%
#1650000
0%
#1655000
b10010000 L
b10010001 M
1%
#1660000
0%
#1665000
b10001111 L
b10010000 M
1%
#1670000
0%
#1675000
b10001110 L
b10001111 M
1%
#1680000
0%
#1685000
b10001101 L
b10001110 M
1%
#1690000
0%
#1695000
b10001100 L
b10001101 M
1%
#1700000
0%
#1705000
b10001011 L
b10001100 M
1%
#1710000
0%
#1715000
b10001010 L
b10001011 M
1%
#1720000
0%
#1725000
b10001001 L
b10001010 M
1%
#1730000
0%
#1735000
b10001000 L
b10001001 M
1%
#1740000
0%
#1745000
b10000111 L
b10001000 M
1%
#1750000
0%
#1755000
b10000110 L
b10000111 M
1%
#1760000
0%
#1765000
b10000101 L
b10000110 M
1%
#1770000
0%
#1775000
b10000100 L
b10000101 M
1%
#1780000
0%
#1785000
b10000011 L
b10000100 M
1%
#1790000
0%
#1795000
b10000010 L
b10000011 M
1%
#1800000
0%
#1805000
b10000001 L
b10000010 M
1%
#1810000
0%
#1815000
b10000000 L
b10000001 M
1%
#1820000
0%
#1825000
b1111111 L
b10000000 M
1%
#1830000
0%
#1835000
b1111110 L
b1111111 M
1%
#1840000
0%
